cf_step/__init__.py
cf_step/_nbdev.py
cf_step/losses.py
cf_step/metrics.py
cf_step/networks.py
cf_step/step.py
cf_step/utils.py
cf_step-0.2.3.dist-info/LICENSE
cf_step-0.2.3.dist-info/METADATA
cf_step-0.2.3.dist-info/WHEEL
cf_step-0.2.3.dist-info/entry_points.txt
cf_step-0.2.3.dist-info/top_level.txt
cf_step-0.2.3.dist-info/RECORD
