Metadata-Version: 2.1
Name: cf-step
Version: 0.2.3
Summary: Incremental collaborative filtering algorithms for recommender systems
Home-page: https://github.com/dpoulopoulos/cf_step
Author: Dimitris Poulopoulos
Author-email: dimitris.a.poulopoulos@gmail.com
License: Apache Software License 2.0
Keywords: recommender systems,recommendation systems,matrix factorization,incremental learning,machine learning,pytorch
Platform: UNKNOWN
Classifier: Development Status :: 4 - Beta
Classifier: Intended Audience :: Developers
Classifier: License :: OSI Approved :: Apache Software License
Classifier: Natural Language :: English
Classifier: Programming Language :: Python :: 3.6
Classifier: Programming Language :: Python :: 3.7
Classifier: Programming Language :: Python :: 3.8
Requires-Python: >=3.6
Requires-Dist: torch (>=1.3.0)
Requires-Dist: tqdm
Requires-Dist: pandas
Requires-Dist: matplotlib
